actions/__init__.py
actions/action.py
github_actions-0.0.1.dist-info/LICENSE
github_actions-0.0.1.dist-info/METADATA
github_actions-0.0.1.dist-info/WHEEL
github_actions-0.0.1.dist-info/top_level.txt
github_actions-0.0.1.dist-info/RECORD
